langchain_cloudflare_vectorize/__init__.py
langchain_cloudflare_vectorize/chat_models.py
langchain_cloudflare_vectorize/document_loaders.py
langchain_cloudflare_vectorize/embeddings.py
langchain_cloudflare_vectorize/py.typed
langchain_cloudflare_vectorize/retrievers.py
langchain_cloudflare_vectorize/toolkits.py
langchain_cloudflare_vectorize/tools.py
langchain_cloudflare_vectorize/vectorstores.py
langchain_cloudflare_vectorize/vectorstores_2.py
langchain_cloudflare_vectorize-0.1.0.dist-info/LICENSE
langchain_cloudflare_vectorize-0.1.0.dist-info/METADATA
langchain_cloudflare_vectorize-0.1.0.dist-info/WHEEL
langchain_cloudflare_vectorize-0.1.0.dist-info/RECORD
